MANIFEST.in
README.md
setup.py
examples/gpio_example.py
lib/mipea/.git
lib/mipea/LICENSE.md
lib/mipea/Makefile.am
lib/mipea/README.md
lib/mipea/TODO
lib/mipea/configure.ac
lib/mipea/src/Makefile.am
lib/mipea/src/clock_manager.c
lib/mipea/src/clock_manager.h
lib/mipea/src/dma.c
lib/mipea/src/dma.h
lib/mipea/src/gpio.c
lib/mipea/src/gpio.h
lib/mipea/src/i2c.c
lib/mipea/src/i2c.h
lib/mipea/src/mailbox_mod.c
lib/mipea/src/mailbox_mod.h
lib/mipea/src/mipea.c
lib/mipea/src/mipea.h
lib/mipea/src/peripherals.c
lib/mipea/src/peripherals.h
lib/mipea/src/pwm.c
lib/mipea/src/pwm.h
lib/mipea/src/spi.c
lib/mipea/src/spi.h
lib/mipea/src/timer.c
lib/mipea/src/timer.h
mipea/__init__.py
mipea/gpiomodule.c
mipea.egg-info/PKG-INFO
mipea.egg-info/SOURCES.txt
mipea.egg-info/dependency_links.txt
mipea.egg-info/top_level.txt