Metadata-Version: 2.1
Name: mipea
Version: 0.1.1
Summary: lightning fast peripheral access on the Raspberry Pi using a mipea wrapper written in C
Home-page: https://github.com/jasLogic/mipeapy
Author: jasLogic
Author-email: jaslo@jaslogic.tech
License: UNKNOWN
Project-URL: Bug Tracker, https://github.com/jasLogic/mipeapy/issues
Project-URL: Source Code, https://github.com/jasLogic/mipeapy
Project-URL: Download, https://github.com/jasLogic/mipeapy/releases
Keywords: c peripheral access Raspberry Pi mipea gpio
Platform: UNKNOWN
Classifier: Development Status :: 2 - Pre-Alpha
Classifier: License :: OSI Approved :: Apache Software License
Classifier: Programming Language :: C
Classifier: Topic :: Software Development :: Libraries
Classifier: Topic :: System :: Hardware
